dogoban/__init__.py
dogoban/__main__.py
dogoban-0.0.1.dist-info/LICENSE
dogoban-0.0.1.dist-info/METADATA
dogoban-0.0.1.dist-info/WHEEL
dogoban-0.0.1.dist-info/top_level.txt
dogoban-0.0.1.dist-info/RECORD
